fastwonn/__init__.py
fastwonn/mle.py
fastwonn/twonn.py
fastwonn/utils.py
fastwonn/impl/__init__.py
fastwonn/impl/faisscpu.py
fastwonn/impl/faissgpu.py
fastwonn/impl/fallback.py
fastwonn/impl/keops.py
fastwonn/impl/pytorch.py
fastwonn/impl/utils.py
fastwonn-0.0.9.dist-info/METADATA
fastwonn-0.0.9.dist-info/WHEEL
fastwonn-0.0.9.dist-info/top_level.txt
fastwonn-0.0.9.dist-info/zip-safe
fastwonn-0.0.9.dist-info/RECORD
