Metadata-Version: 2.1
Name: fastwonn
Version: 0.0.9
Summary: Fast, GPU-friendly, differentiable computation of Intrinsic Dimension via Maximum Likelihood, the TwoNN algorithm, and everything in between!
Home-page: https://github.com/emaballarin/fastwonn
Author: Emanuele Ballarin
Author-email: emanuele@ballarin.cc
License: MIT
Keywords: Deep Learning,Differentiable Programming,Intrinsic Dimension,Machine Learning,Manifold Learning,Maximum Likelihood Estimation,PyTorch,TwoNN
Classifier: Development Status :: 4 - Beta
Classifier: Topic :: Scientific/Engineering :: Mathematics
Classifier: Environment :: Console
Classifier: Programming Language :: Python :: 3
Classifier: License :: OSI Approved :: MIT License
Requires-Python: >=3.10
Requires-Dist: torch >=2
Requires-Dist: torchsort >=0.1.9
Provides-Extra: faiss_cpu
Requires-Dist: faiss-cpu >=1.8.0 ; extra == 'faiss_cpu'
Provides-Extra: faiss_gpu_newer_cu11
Requires-Dist: faiss-gpu-cu11 >=1.8.0.2 ; extra == 'faiss_gpu_newer_cu11'
Provides-Extra: faiss_gpu_newer_cu12
Requires-Dist: faiss-gpu-cu12 >=1.8.0.2 ; extra == 'faiss_gpu_newer_cu12'
Provides-Extra: faiss_gpu_older
Requires-Dist: faiss-gpu >=1.7.2 ; extra == 'faiss_gpu_older'
Provides-Extra: keops
Requires-Dist: keopscore >=2.2.3 ; extra == 'keops'
Requires-Dist: pykeops >=2.2.3 ; extra == 'keops'
